{
    "version": "p20220503",
    "description": "An AV1 video encoder designed to eventually cover all use cases.",
    "homepage": "https://github.com/xiph/rav1e",
    "license": "BSD-2-Clause",
    "architecture": {
        "64bit": {
            "url": "https://github.com/xiph/rav1e/releases/download/p20220503/rav1e.exe",
            "hash": "ea0f8a7be7c57b098402ea604cb2784c468878e1eca72072e6c9705b21644573"
        }
    },
    "bin": "rav1e.exe",
    "checkver": {
        "url": "https://github.com/xiph/rav1e/releases",
        "regex": "tag/(?<version>p[\\d.]+)"
    },
    "autoupdate": {
        "architecture": {
            "64bit": {
                "url": "https://github.com/xiph/rav1e/releases/download/$version/rav1e.exe"
            }
        }
    }
}
